deepfake_detector/__init__.py
deepfake_detector/face_detection.py
deepfake_detector/model.py
deepfake_detector/utils.py
Deepfake_detector-1.4.dist-info/METADATA
Deepfake_detector-1.4.dist-info/WHEEL
Deepfake_detector-1.4.dist-info/top_level.txt
Deepfake_detector-1.4.dist-info/RECORD
