Metadata-Version: 2.1
Name: Deepfake-detector
Version: 1.4
Summary: A Python library for detecting deepfake images and videos.
Home-page: https://github.com/saiadupa/Deepfake-detector
Author: Adupa Nithin Sai
Author-email: adupanithinsai@gmail.com
Classifier: Programming Language :: Python :: 3.11
Classifier: Operating System :: OS Independent
Classifier: Intended Audience :: Developers
Classifier: Topic :: Software Development :: Libraries :: Python Modules
Requires-Python: >=3
Requires-Dist: tensorflow (==2.13.0)
Requires-Dist: opencv-python (==4.10.0.84)
Requires-Dist: numpy (==1.24.3)
Requires-Dist: matplotlib (==3.9.2)
Requires-Dist: gdown
